mcglm/__init__.py
mcglm/dependencies.py
mcglm/mcglm.py
mcglm/mcglmcattr.py
mcglm/mcglmmean.py
mcglm/mcglmvariance.py
mcglm/utils.py
mcglm-0.2.4.dist-info/LICENSE.txt
mcglm-0.2.4.dist-info/WHEEL
mcglm-0.2.4.dist-info/METADATA
mcglm-0.2.4.dist-info/RECORD
