Metadata-Version: 2.1
Name: mcglm
Version: 0.2.4
Summary: Multivariate Covariance Generalized Linear Models
Author: Jean Carlos Faoot Maia
Author-email: jeanclmaia@gmail.com
Requires-Python: >=3.9
Classifier: Programming Language :: Python :: 3
Classifier: Programming Language :: Python :: 3.10
Classifier: Programming Language :: Python :: 3.9
Requires-Dist: matplotlib (>=3.5.2,<4.0.0)
Requires-Dist: numpy (>=1.25,<2.0)
Requires-Dist: pandas (>=1.3.3,<2.0.0)
Requires-Dist: patsy (>=0.5.2,<0.6.0)
Requires-Dist: statsmodels (>=0.13.2,<0.14.0)
